confluentcloud_iam_serviceaccount/__init__.py
confluentcloud_iam_serviceaccount/handlers.py
confluentcloud_iam_serviceaccount/models.py
confluentcloud_iam_serviceaccount/resource.py
confluentcloud_iam_serviceaccount-1.0.0.post0.dist-info/LICENSE
confluentcloud_iam_serviceaccount-1.0.0.post0.dist-info/WHEEL
confluentcloud_iam_serviceaccount-1.0.0.post0.dist-info/METADATA
confluentcloud_iam_serviceaccount-1.0.0.post0.dist-info/RECORD
