Metadata-Version: 2.1
Name: confluentcloud-iam-serviceaccount
Version: 1.0.0.post0
Summary: AWS CFN Resource to provision a Confluent Cloud Service account
License: LICENSE
Keywords: aws,cloudformation,kafka,confluent
Author: John Preston
Author-email: john@ews-network.net
Requires-Python: >=3.7,<4.0
Classifier: Development Status :: 4 - Beta
Classifier: Intended Audience :: Developers
Classifier: Intended Audience :: Information Technology
Classifier: Intended Audience :: System Administrators
Classifier: License :: OSI Approved :: GNU General Public License v2 (GPLv2)
Classifier: License :: Other/Proprietary License
Classifier: Natural Language :: English
Classifier: Programming Language :: Python :: 3
Classifier: Programming Language :: Python :: 3.10
Classifier: Programming Language :: Python :: 3.7
Classifier: Programming Language :: Python :: 3.8
Classifier: Programming Language :: Python :: 3.9
Provides-Extra: resource
Requires-Dist: cloudformation-cli-python-lib (>=2.1.11,<3.0.0)
Requires-Dist: compose-x-common (>=0.4.2,<0.5.0)
Requires-Dist: confluent-cloud-sdk (>=0.1.0,<0.2.0)
Requires-Dist: troposphere (>=4.0.1,<5.0.0); extra == "resource"
